tap_bitly/__init__.py
tap_bitly/client.py
tap_bitly/streams.py
tap_bitly/tap.py
tap_bitly/openapi/__init__.py
tap_bitly/openapi/openapi.json
tap_bitly-0.5.0.dist-info/METADATA
tap_bitly-0.5.0.dist-info/WHEEL
tap_bitly-0.5.0.dist-info/entry_points.txt
tap_bitly-0.5.0.dist-info/licenses/LICENSE
tap_bitly-0.5.0.dist-info/RECORD
