Metadata-Version: 2.4
Name: tap-bitly
Version: 0.5.0
Summary: Singer tap for Bitly, built with the Meltano SDK for Singer Taps.
Project-URL: Documentation, https://github.com/reservoir-data/tap-bitly#readme
Project-URL: Homepage, https://github.com/reservoir-data/tap-bitly
Project-URL: Repository, https://github.com/reservoir-data/tap-bitly
Author-email: Edgar Ramirez-Mondragon <edgarrm358@gmail.com>
Maintainer-email: Edgar Ramirez-Mondragon <edgarrm358@gmail.com>
License-Expression: Apache-2.0
License-File: LICENSE
Keywords: Bitly,ELT,singer.io
Classifier: Programming Language :: Python :: 3 :: Only
Classifier: Programming Language :: Python :: 3.12
Classifier: Programming Language :: Python :: 3.13
Classifier: Programming Language :: Python :: 3.14
Requires-Python: >=3.12
Requires-Dist: singer-sdk~=0.53.2
